Ordenamiento/Funciones.py
Ordenamiento/__init__.py
Ordenamiento-0.0.1.dist-info/METADATA
Ordenamiento-0.0.1.dist-info/WHEEL
Ordenamiento-0.0.1.dist-info/top_level.txt
Ordenamiento-0.0.1.dist-info/RECORD
