Metadata-Version: 2.1
Name: Ordenamiento
Version: 0.0.1
Home-page: https://github.com/AbdielLopezVilla
Author: Abdiel López Villa
Author-email: 212t0218@itsm.edu.mx
License: MIT
Requires-Dist: numpy
